biopeaks/__main__.py
biopeaks/analysis_utils.py
biopeaks/benchmarks/benchmark_ECG_local.py
biopeaks/benchmarks/benchmark_ECG_stream.py
biopeaks/benchmarks/benchmark_PPG_local.py
biopeaks/controller.py
biopeaks/filters.py
biopeaks/heart.py
biopeaks/images/file_icon.png
biopeaks/images/mouse_icon.png
biopeaks/images/python_icon.ico
biopeaks/images/python_icon.png
biopeaks/io_utils.py
biopeaks/model.py
biopeaks/resources.py
biopeaks/resp.py
biopeaks/tests/test_gui.py
biopeaks/tests/test_heart.py
biopeaks/tests/test_resp.py
biopeaks/tests/testdata/EDFmontage0.edf
biopeaks/tests/testdata/OSmontage0J.txt
biopeaks/tests/testdata/OSmontage1A.txt
biopeaks/tests/testdata/OSmontage1J.txt
biopeaks/tests/testdata/OSmontage2A.txt
biopeaks/tests/testdata/OSmontage2J.txt
biopeaks/tests/testdata/OSmontage3A.txt
biopeaks/tests/testdata/OSmontage3J.txt
biopeaks/tests/testdata/OSmontagePPG.txt
biopeaks/view.py
biopeaks-1.4.4.dist-info/entry_points.txt
biopeaks-1.4.4.dist-info/LICENSE
biopeaks-1.4.4.dist-info/WHEEL
biopeaks-1.4.4.dist-info/METADATA
biopeaks-1.4.4.dist-info/RECORD
