Metadata-Version: 2.1
Name: biopeaks
Version: 1.4.4
Summary: A graphical user interface for feature extraction from heart- and breathing biosignals.
Home-page: https://github.com/JanCBrammer/biopeaks
License: GPL-3.0
Keywords: ECG,PPG,Breathing,Biosignals,GUI
Author: Jan C. Brammer
Author-email: jan.c.brammer@gmail.com
Requires-Python: >=3.9,<3.11
Classifier: License :: OSI Approved :: GNU General Public License v3 (GPLv3)
Classifier: Programming Language :: Python :: 3
Classifier: Programming Language :: Python :: 3.10
Classifier: Programming Language :: Python :: 3.9
Provides-Extra: pyinstaller
Requires-Dist: PySide6 (>=6.2.2)
Requires-Dist: matplotlib (>=3.5.0)
Requires-Dist: numpy (>=1.22.0)
Requires-Dist: pandas (>=1.3.5)
Requires-Dist: pyinstaller (>=4.7); extra == "pyinstaller"
Requires-Dist: scipy (>=1.7.3)
Project-URL: Documentation, https://jancbrammer.github.io/biopeaks
Project-URL: Repository, https://github.com/JanCBrammer/biopeaks
